samplehc/__init__.py
samplehc/_base_client.py
samplehc/_client.py
samplehc/_compat.py
samplehc/_constants.py
samplehc/_exceptions.py
samplehc/_files.py
samplehc/_models.py
samplehc/_qs.py
samplehc/_resource.py
samplehc/_response.py
samplehc/_streaming.py
samplehc/_types.py
samplehc/_version.py
samplehc/py.typed
samplehc/_utils/__init__.py
samplehc/_utils/_compat.py
samplehc/_utils/_datetime_parse.py
samplehc/_utils/_logs.py
samplehc/_utils/_proxy.py
samplehc/_utils/_reflection.py
samplehc/_utils/_resources_proxy.py
samplehc/_utils/_streams.py
samplehc/_utils/_sync.py
samplehc/_utils/_transform.py
samplehc/_utils/_typing.py
samplehc/_utils/_utils.py
samplehc/lib/.keep
samplehc/resources/__init__.py
samplehc/resources/v2/__init__.py
samplehc/resources/v2/async_results.py
samplehc/resources/v2/communication.py
samplehc/resources/v2/database.py
samplehc/resources/v2/events.py
samplehc/resources/v2/v2.py
samplehc/resources/v2/documents/__init__.py
samplehc/resources/v2/documents/documents.py
samplehc/resources/v2/documents/formats.py
samplehc/resources/v2/documents/legacy.py
samplehc/resources/v2/documents/templates.py
samplehc/types/__init__.py
samplehc/types/v2/__init__.py
samplehc/types/v2/async_result_sleep_params.py
samplehc/types/v2/async_result_sleep_response.py
samplehc/types/v2/communication_send_email_params.py
samplehc/types/v2/communication_send_email_response.py
samplehc/types/v2/communication_send_fax_params.py
samplehc/types/v2/communication_send_fax_response.py
samplehc/types/v2/communication_send_letter_params.py
samplehc/types/v2/communication_send_letter_response.py
samplehc/types/v2/database_execute_sql_params.py
samplehc/types/v2/database_execute_sql_response.py
samplehc/types/v2/document_classify_params.py
samplehc/types/v2/document_classify_response.py
samplehc/types/v2/document_combine_params.py
samplehc/types/v2/document_combine_response.py
samplehc/types/v2/document_create_from_splits_params.py
samplehc-0.18.0.dist-info/METADATA
samplehc-0.18.0.dist-info/WHEEL
samplehc-0.18.0.dist-info/licenses/LICENSE
samplehc-0.18.0.dist-info/RECORD
